pydataforgehub/__init__.py
pydataforgehub/cli.py
pydataforgehub/data_analysis.py
pydataforgehub/data_count.py
pydataforgehub/data_quality.py
pydataforgehub/data_visualization.py
pydataforgehub/pydataforgehub.py
pydataforgehub-0.1.2.dist-info/AUTHORS.rst
pydataforgehub-0.1.2.dist-info/LICENSE
pydataforgehub-0.1.2.dist-info/METADATA
pydataforgehub-0.1.2.dist-info/WHEEL
pydataforgehub-0.1.2.dist-info/top_level.txt
pydataforgehub-0.1.2.dist-info/RECORD
