Metadata-Version: 2.1
Name: pydataforgehub
Version: 0.1.2
Summary: PyDataForgeHub automates data quality checks, analysis, and visualization. It simplifies data management workflows and improves accuracy in data-driven projects.
Author-email: Mirwais Farahi <waisfarahi@gmail.com>
Maintainer-email: Mirwais Farahi <waisfarahi@gmail.com>
License: MIT license
Project-URL: bugs, https://github.com/Mirwais-Farahi/pydataforgehub/issues
Project-URL: changelog, https://github.com/Mirwais-Farahi/pydataforgehub/blob/master/changelog.md
Project-URL: homepage, https://github.com/Mirwais-Farahi/pydataforgehub
License-File: LICENSE
License-File: AUTHORS.rst
Requires-Dist: typer
Requires-Dist: pandas
Requires-Dist: matplotlib
Provides-Extra: dev
Requires-Dist: coverage; extra == "dev"
Requires-Dist: mypy; extra == "dev"
Requires-Dist: pytest; extra == "dev"
Requires-Dist: ruff; extra == "dev"
